LICENSE.txt
MANIFEST.in
README.rst
pyproject.toml
setup.py
include/raprif.h
psntools/__init__.py
psntools/raprif.py
psntools.egg-info/PKG-INFO
psntools.egg-info/SOURCES.txt
psntools.egg-info/dependency_links.txt
psntools.egg-info/top_level.txt
src/raprif.c
src/raprifPYTHON_wrap.c