Metadata-Version: 2.1
Name: psntools
Version: 1.0.0
Summary: Library functions for PSN packages
Home-page: https://github.com/windsurfer1122/psntools
Author: windsurfer1122
Author-email: windsurfer1122@example.com
License: UNKNOWN
Keywords: PSN,PS3,RAP,RIF
Platform: UNKNOWN
Classifier: Development Status :: 5 - Production/Stable
Classifier: Intended Audience :: Developers
Classifier: License :: OSI Approved :: GNU General Public License v3 or later (GPLv3+)
Classifier: Operating System :: POSIX :: Linux
Classifier: Operating System :: MacOS :: MacOS X
Classifier: Operating System :: Microsoft :: Windows
Classifier: Programming Language :: Python :: 2.7
Classifier: Programming Language :: Python :: 3
Classifier: Programming Language :: C
Classifier: Topic :: Software Development :: Libraries :: Python Modules
Requires-Python: >=2.7
License-File: LICENSE.txt
